subtitles/__init__.py
subtitles/subtitle_track.py
subtitles/subtitles.py
pyqt_subtitles-1.2.dist-info/METADATA
pyqt_subtitles-1.2.dist-info/WHEEL
pyqt_subtitles-1.2.dist-info/licenses/LICENSE
pyqt_subtitles-1.2.dist-info/RECORD
