Metadata-Version: 2.4
Name: pyqt-subtitles
Version: 1.2
Summary: Python library for adding srt subtitles into QMediaPlayer
Project-URL: Homepage, https://github.com/nchistov/pyqt-subtitles
Project-URL: Issues, https://github.com/nchistov/pyqt-subtitles/issues
Author-email: Nickolay Chistov <nickolaychistov@gmail.com>
License-Expression: MIT
License-File: LICENSE
Classifier: Operating System :: OS Independent
Classifier: Programming Language :: Python :: 3
Requires-Dist: pyqt6
Requires-Dist: srt
